boar/__init__.py
boar/linting.py
boar/run.py
boar/running.py
boar/testing.py
boar/utils/__init__.py
boar/utils/apply.py
boar/utils/execute.py
boar/utils/log.py
boar/utils/parse.py
boar/utils/split.py
boar-0.0.1.dist-info/LICENSE
boar-0.0.1.dist-info/METADATA
boar-0.0.1.dist-info/WHEEL
boar-0.0.1.dist-info/top_level.txt
boar-0.0.1.dist-info/RECORD
