Metadata-Version: 2.1
Name: boar
Version: 0.0.1
Summary: Dirty tricks to run python notebooks
Home-page: UNKNOWN
Author: Alexandre Cameron
Author-email: lexcam@hotmail.fr
License: UNKNOWN
Platform: UNKNOWN
Classifier: Programming Language :: Python :: 3
Classifier: License :: OSI Approved :: MIT License
Classifier: Operating System :: OS Independent
Requires-Python: >=3.6
